brasil.gov.facetada-1.0b1-py2.7-nspkg.pth
brasil/gov/facetada/__init__.py
brasil/gov/facetada/at_widgets.py
brasil/gov/facetada/config.py
brasil/gov/facetada/configure.zcml
brasil/gov/facetada/dependencies.zcml
brasil/gov/facetada/interfaces.py
brasil/gov/facetada/profiles.zcml
brasil/gov/facetada/skins.zcml
brasil/gov/facetada/testing.py
brasil/gov/facetada/vocabulary.py
brasil/gov/facetada/browser/__init__.py
brasil/gov/facetada/browser/configure.zcml
brasil/gov/facetada/browser/faceted/__init__.py
brasil/gov/facetada/browser/faceted/configure.zcml
brasil/gov/facetada/browser/faceted/summary.pt
brasil/gov/facetada/browser/scaleimage/__init__.py
brasil/gov/facetada/browser/scaleimage/configure.zcml
brasil/gov/facetada/browser/scaleimage/scaleimage.py
brasil/gov/facetada/faceted/__init__.py
brasil/gov/facetada/faceted/configure.zcml
brasil/gov/facetada/faceted/widgets/__init__.py
brasil/gov/facetada/faceted/widgets/configure.zcml
brasil/gov/facetada/faceted/widgets/banner/__init__.py
brasil/gov/facetada/faceted/widgets/banner/configure.zcml
brasil/gov/facetada/faceted/widgets/banner/view.js
brasil/gov/facetada/faceted/widgets/banner/widget.pt
brasil/gov/facetada/faceted/widgets/banner/widget.py
brasil/gov/facetada/faceted/widgets/ordenar/__init__.py
brasil/gov/facetada/faceted/widgets/ordenar/configure.zcml
brasil/gov/facetada/faceted/widgets/ordenar/edit.js
brasil/gov/facetada/faceted/widgets/ordenar/view.css
brasil/gov/facetada/faceted/widgets/ordenar/view.js
brasil/gov/facetada/faceted/widgets/ordenar/widget.pt
brasil/gov/facetada/faceted/widgets/ordenar/widget.py
brasil/gov/facetada/profiles/default/browserlayer.xml
brasil/gov/facetada/profiles/default/cssregistry.xml
brasil/gov/facetada/profiles/default/jsregistry.xml
brasil/gov/facetada/profiles/default/metadata.xml
brasil/gov/facetada/profiles/default/skins.xml
brasil/gov/facetada/profiles/uninstall/brasil.gov.facetada.txt
brasil.gov.facetada-1.0b1.dist-info/DESCRIPTION.rst
brasil.gov.facetada-1.0b1.dist-info/METADATA
brasil.gov.facetada-1.0b1.dist-info/RECORD
brasil.gov.facetada-1.0b1.dist-info/WHEEL
brasil.gov.facetada-1.0b1.dist-info/entry_points.txt
brasil.gov.facetada-1.0b1.dist-info/metadata.json
brasil.gov.facetada-1.0b1.dist-info/namespace_packages.txt
brasil.gov.facetada-1.0b1.dist-info/top_level.txt
