Metadata-Version: 2.0
Name: brasil.gov.facetada
Version: 1.0b1
Summary: Suporte à busca multifacetada para Portal Padrão
Home-page: https://github.com/plonegovbr/brasil.gov.facetada
Author: PloneGovBr
Author-email: gov@plone.org.br
License: UNKNOWN
Keywords: plonegovbr busca facetada multifacetada
Platform: UNKNOWN
Classifier: Development Status :: 3 - Alpha
Classifier: Environment :: Web Environment
Classifier: Framework :: Plone
Classifier: Framework :: Plone :: 4.3
Classifier: Intended Audience :: System Administrators
Classifier: License :: OSI Approved :: GNU General Public License v2 (GPLv2)
Classifier: Operating System :: OS Independent
Classifier: Programming Language :: Python
Classifier: Programming Language :: Python :: 2.7
Classifier: Topic :: Software Development :: Libraries :: Python Modules
Requires-Dist: Products.CMFPlone (>=4.3)
Requires-Dist: Products.GenericSetup
Requires-Dist: eea.facetednavigation (<10)
Requires-Dist: five.grok
Requires-Dist: five.pt
Requires-Dist: plone.api
Requires-Dist: plone.app.contenttypes
Requires-Dist: plone.app.upgrade
Requires-Dist: setuptools
Requires-Dist: zope.i18nmessageid
Requires-Dist: zope.interface
Provides-Extra: test
Requires-Dist: plone.app.robotframework; extra == 'test'
Requires-Dist: plone.app.testing[robot] (>=4.2.2); extra == 'test'
Requires-Dist: plone.browserlayer; extra == 'test'
Requires-Dist: plone.testing; extra == 'test'
Requires-Dist: robotsuite; extra == 'test'
